gscan/__init__.py
gscan/__version__.py
gscan/main.py
gscan/bin/gscan-darwin-amd64
gscan/bin/gscan-darwin-arm64
gscan/bin/gscan-linux-386
gscan/bin/gscan-linux-amd64
gscan/bin/gscan-linux-arm64
gscan/bin/gscan-windows-386.exe
gscan/bin/gscan-windows-amd64.exe
gscan-0.3.3.dist-info/LICENSE
gscan-0.3.3.dist-info/METADATA
gscan-0.3.3.dist-info/WHEEL
gscan-0.3.3.dist-info/entry_points.txt
gscan-0.3.3.dist-info/top_level.txt
gscan-0.3.3.dist-info/RECORD
