Metadata-Version: 2.1
Name: gscan
Version: 0.3.3
Summary: A golang scanner
Author: lanXuage & YuSec2021
Author-email: lanxuage@gmail.com
License: MIT
Keywords: scan,golang
License-File: LICENSE
